lektor_simplemde.py
lektor_simplemde-0.6.dist-info/LICENSE
lektor_simplemde-0.6.dist-info/METADATA
lektor_simplemde-0.6.dist-info/WHEEL
lektor_simplemde-0.6.dist-info/entry_points.txt
lektor_simplemde-0.6.dist-info/top_level.txt
lektor_simplemde-0.6.dist-info/RECORD
