Metadata-Version: 2.1
Name: lektor-simplemde
Version: 0.6
Summary: Plugin integrating SimpleMDE into Lektor admin
Home-page: UNKNOWN
Author: Anton Patrushev
Author-email: ap@spherical.pm
Maintainer: spherical.pm
Maintainer-email: support@spherical.pm
License: MIT
Keywords: Lektor admin plugin simplemde wysiwyg markdown editor
Platform: UNKNOWN
Classifier: Framework :: Lektor
Classifier: Environment :: Plugins
Provides-Extra: dev
Requires-Dist: spherical-dev[dev] (<0.3,>=0.2.2) ; extra == 'dev'
